orign/__init__.py
orign/auth.py
orign/config.py
orign/actors/actor.py
orign/actors/img.py
orign/actors/models.py
orign/actors/state.py
orign/adapters/adapter.py
orign/adapters/models.py
orign/agents/__init__.py
orign/agents/adaptive.py
orign/buffers/buffer.py
orign/buffers/models.py
orign/humans/human.py
orign/humans/models.py
orign/llms/llm.py
orign/llms/models.py
orign/mcp/__init__.py
orign/mcp/sync.py
orign/tasks/models.py
orign/tasks/task.py
orign/trainings/models.py
orign/trainings/training.py
orign/zoo/__init__.py
orign/zoo/trl.py
orign/zoo/vllm.py
orign/zoo/llms/gemma3.py
orign/zoo/llms/qwen_vl.py
orign/zoo/processors/online_training.py
orign/zoo/processors/qwen_server.py
orign/zoo/processors/qwen_server_v0.py
orign/zoo/processors/unsloth_trainer.py
orign/zoo/processors/unsloth_trainer_v0.py
orign/zoo/processors/vllm_server.py
orign-0.2.140.dist-info/licenses/LICENSE
orign-0.2.140.dist-info/METADATA
orign-0.2.140.dist-info/WHEEL
orign-0.2.140.dist-info/top_level.txt
orign-0.2.140.dist-info/RECORD
