Metadata-Version: 2.4
Name: orign
Version: 0.2.140
Summary: Adaptive Agents
Requires-Python: >=3.11.0
License-File: LICENSE
Requires-Dist: chatmux==0.1.3
Requires-Dist: loguru>=0.7.3
Requires-Dist: namesgenerator>=0.3
Requires-Dist: nebulous-sh==0.1.148
Requires-Dist: pillow>=10.4.0
Requires-Dist: pydantic>=2.11.0
Requires-Dist: pyyaml>=6.0.2
Requires-Dist: rclone-python>=0.1.21
Requires-Dist: shortuuid>=1.0.13
Provides-Extra: gcs
Requires-Dist: google-cloud-storage; extra == "gcs"
Requires-Dist: google-api-core; extra == "gcs"
Dynamic: license-file
